fiddler/__init__.py
fiddler/logger.py
crlo-0.1.1.dist-info/LICENSE.txt
crlo-0.1.1.dist-info/METADATA
crlo-0.1.1.dist-info/WHEEL
crlo-0.1.1.dist-info/top_level.txt
crlo-0.1.1.dist-info/RECORD
