Metadata-Version: 2.1
Name: crlo
Version: 0.1.1
Summary: AIOps SDK in Python.
Home-page: https://github.com/uptimedog/crlo/
Author: Clivern
Author-email: hello@clivern.com
License: MIT
Project-URL: Documentation, https://github.com/uptimedog/crlo/
Project-URL: Source, https://github.com/uptimedog/crlo/
Project-URL: Changelog, https://github.com/uptimedog/crlo/blob/main/CHANGELOG.rst
Project-URL: Tracker, https://github.com/uptimedog/crlo/issues
Project-URL: Download, https://pypi.org/project/crlo/#files
Platform: any
Classifier: Development Status :: 5 - Production/Stable
Classifier: Programming Language :: Python
Classifier: License :: OSI Approved :: MIT License
License-File: LICENSE.txt
Requires-Dist: requests
Requires-Dist: importlib-metadata ; python_version < "3.8"
